["```\n{ \n    \"Effect\": \"Allow\", \n    \"Action\": [ \n      \"ec2messages:AcknowledgeMessage\", \n      \"ec2messages:DeleteMessage\", \n      \"ec2messages:FailMessage\", \n      \"ec2messages:GetEndpoint\", \n      \"ec2messages:GetMessages\", \n      \"ec2messages:SendReply\" \n    ], \n    \"Resource\": \"*\" \n}, \n```", "```\n{ \n    \"Effect\": \"Allow\", \n    \"Action\": [ \n      \"ec2messages:AcknowledgeMessage\", \n      \"ec2messages:DeleteMessage\", \n      \"ec2messages:FailMessage\", \n      \"ec2messages:GetEndpoint\", \n      \"ec2messages:GetMessages\", \n      \"ec2messages:SendReply\" \n    ], \n    \"Resource\": \"*\" \n}, \n```", "```\n# wget https://s3.amazonaws.com/ec2-downloads-windows/SSMAgent/latest/debian_amd64/amazon-ssm-agent.deb\n```"]